AUTHORS.rst
CONTRIBUTING.rst
HISTORY.rst
LICENSE
MANIFEST.in
README.rst
requirements.txt
requirements_dev.txt
setup.cfg
setup.py
jh_stackformation.egg-info/PKG-INFO
jh_stackformation.egg-info/SOURCES.txt
jh_stackformation.egg-info/dependency_links.txt
jh_stackformation.egg-info/entry_points.txt
jh_stackformation.egg-info/not-zip-safe
jh_stackformation.egg-info/requires.txt
jh_stackformation.egg-info/top_level.txt
stackformation/__init__.py
stackformation/cli.py
stackformation/utils.py
stackformation/aws/__init__.py
stackformation/aws/user_data.py
stackformation/aws/stacks/__init__.py
stackformation/aws/stacks/alarms.py
stackformation/aws/stacks/alb.py
stackformation/aws/stacks/apigateway.py
stackformation/aws/stacks/asg.py
stackformation/aws/stacks/awslambda.py
stackformation/aws/stacks/cloudfront.py
stackformation/aws/stacks/cloudwatch.py
stackformation/aws/stacks/codedeploy.py
stackformation/aws/stacks/codepipeline.py
stackformation/aws/stacks/dynamodb.py
stackformation/aws/stacks/ebs.py
stackformation/aws/stacks/ec2.py
stackformation/aws/stacks/ecs.py
stackformation/aws/stacks/eip.py
stackformation/aws/stacks/elasticache.py
stackformation/aws/stacks/elb.py
stackformation/aws/stacks/eni.py
stackformation/aws/stacks/iam.py
stackformation/aws/stacks/logs.py
stackformation/aws/stacks/rds.py
stackformation/aws/stacks/route53.py
stackformation/aws/stacks/s3.py
stackformation/aws/stacks/sns.py
stackformation/aws/stacks/sqs.py
stackformation/aws/stacks/ssm.py
stackformation/aws/stacks/vpc.py
stackformation/deploy/__init__.py
tests/__init__.py
tests/test_aws.py
tests/test_aws_stacks_alarms.py
tests/test_aws_stacks_asg.py
tests/test_aws_stacks_codedeploy.py
tests/test_aws_stacks_ebs.py
tests/test_aws_stacks_ec2.py
tests/test_aws_stacks_ecs.py
tests/test_aws_stacks_eip.py
tests/test_aws_stacks_elb.py
tests/test_aws_stacks_iam.py
tests/test_aws_stacks_logs.py
tests/test_aws_stacks_sns.py
tests/test_aws_stacks_vpc.py
tests/test_aws_user_data.py
tests/test_stackformation.py