Metadata-Version: 1.1
Name: jh-stackformation
Version: 0.2.43
Summary: AWS CloudFormation framework
Home-page: https://github.com/ibejohn818/stackformation
Author: John Hardy
Author-email: john@johnchardy.com
License: MIT license
Keywords: stackformation
Platform: UNKNOWN
Classifier: Development Status :: 4 - Beta
Classifier: Intended Audience :: Developers
Classifier: License :: OSI Approved :: MIT License
Classifier: Natural Language :: English
Classifier: Programming Language :: Python :: 3.5
